graphrag/__init__.py
graphrag/__main__.py
graphrag/api/__init__.py
graphrag/api/index.py
graphrag/api/prompt_tune.py
graphrag/api/query.py
graphrag/cache/__init__.py
graphrag/cache/factory.py
graphrag/cache/json_pipeline_cache.py
graphrag/cache/memory_pipeline_cache.py
graphrag/cache/noop_pipeline_cache.py
graphrag/cache/pipeline_cache.py
graphrag/callbacks/__init__.py
graphrag/callbacks/blob_workflow_callbacks.py
graphrag/callbacks/console_workflow_callbacks.py
graphrag/callbacks/factory.py
graphrag/callbacks/file_workflow_callbacks.py
graphrag/callbacks/global_search_callbacks.py
graphrag/callbacks/llm_callbacks.py
graphrag/callbacks/noop_workflow_callbacks.py
graphrag/callbacks/progress_workflow_callbacks.py
graphrag/callbacks/workflow_callbacks.py
graphrag/callbacks/workflow_callbacks_manager.py
graphrag/cli/__init__.py
graphrag/cli/index.py
graphrag/cli/initialize.py
graphrag/cli/main.py
graphrag/cli/prompt_tune.py
graphrag/cli/query.py
graphrag/config/__init__.py
graphrag/config/config_file_loader.py
graphrag/config/create_graphrag_config.py
graphrag/config/defaults.py
graphrag/config/enums.py
graphrag/config/environment_reader.py
graphrag/config/errors.py
graphrag/config/init_content.py
graphrag/config/load_config.py
graphrag/config/logging.py
graphrag/config/models/__init__.py
graphrag/config/models/basic_search_config.py
graphrag/config/models/cache_config.py
graphrag/config/models/chunking_config.py
graphrag/config/models/claim_extraction_config.py
graphrag/config/models/cluster_graph_config.py
graphrag/config/models/community_reports_config.py
graphrag/config/models/drift_search_config.py
graphrag/config/models/embed_graph_config.py
graphrag/config/models/entity_extraction_config.py
graphrag/config/models/global_search_config.py
graphrag/config/models/graph_rag_config.py
graphrag/config/models/input_config.py
graphrag/config/models/llm_config.py
graphrag/config/models/llm_parameters.py
graphrag/config/models/local_search_config.py
graphrag_more-1.2.0.dist-info/LICENSE
graphrag_more-1.2.0.dist-info/METADATA
graphrag_more-1.2.0.dist-info/WHEEL
graphrag_more-1.2.0.dist-info/entry_points.txt
graphrag_more-1.2.0.dist-info/RECORD
