Metadata-Version: 2.1
Name: graphrag-more
Version: 1.2.0
Summary: 基于微软GraphRAG，支持使用百度千帆、阿里通义、Ollama、字节豆包等大模型服务
Home-page: https://github.com/guoyao/graphrag-more
License: MIT
Author: Guoyao Wu
Author-email: guoyao.me@gmail.com
Requires-Python: >=3.10,<3.13
Classifier: License :: OSI Approved :: MIT License
Classifier: Programming Language :: Python :: 3
Classifier: Programming Language :: Python :: 3.10
Classifier: Programming Language :: Python :: 3.11
Classifier: Programming Language :: Python :: 3.12
Requires-Dist: aiofiles (>=24.1.0,<25.0.0)
Requires-Dist: azure-cosmos (>=4.9.0,<5.0.0)
Requires-Dist: azure-identity (>=1.19.0,<2.0.0)
Requires-Dist: azure-search-documents (>=11.5.2,<12.0.0)
Requires-Dist: azure-storage-blob (>=12.24.0,<13.0.0)
Requires-Dist: devtools (>=0.12.2,<0.13.0)
Requires-Dist: environs (>=11.0.0,<12.0.0)
Requires-Dist: fnllm (>=0.0.10,<0.0.11)
Requires-Dist: future (>=1.0.0,<2.0.0)
Requires-Dist: graspologic (>=3.4.1,<4.0.0)
Requires-Dist: httpx (>=0.28.1,<0.29.0)
Requires-Dist: json-repair (>=0.30.3,<0.31.0)
Requires-Dist: lancedb (>=0.17.0,<0.18.0)
Requires-Dist: networkx (>=3.4.2,<4.0.0)
Requires-Dist: nltk (==3.9.1)
Requires-Dist: numpy (>=1.25.2,<2.0.0)
Requires-Dist: openai (>=1.57.0,<2.0.0)
Requires-Dist: pandas (>=2.2.3,<3.0.0)
Requires-Dist: pyarrow (>=15.0.0,<16.0.0)
Requires-Dist: pydantic (>=2.10.3,<3.0.0)
Requires-Dist: python-dotenv (>=1.0.1,<2.0.0)
Requires-Dist: pyyaml (>=6.0.2,<7.0.0)
Requires-Dist: rich (>=13.9.4,<14.0.0)
Requires-Dist: tenacity (>=8.5.0,<9.0.0)
Requires-Dist: tiktoken (>=0.8.0,<0.9.0)
Requires-Dist: tqdm (>=4.67.1,<5.0.0)
Requires-Dist: typer (>=0.15.1,<0.16.0)
Requires-Dist: typing-extensions (>=4.12.2,<5.0.0)
Requires-Dist: umap-learn (>=0.5.6,<0.6.0)
Project-URL: Repository, https://github.com/guoyao/graphrag-more
Project-URL: Source, https://github.com/guoyao/graphrag-more
